{
  "ReRoutes": [
    {
      "DownstreamPathTemplate": "/api/{catchAll}",
      "DownstreamScheme": "http",
      "DownstreamHostAndPorts": [
        {
          "Host": "host.docker.internal",
          "Port": 50001
        }
      ],
      "UpstreamPathTemplate": "/users-api/{catchAll}"
    },
    {
      "DownstreamPathTemplate": "/api/{catchAll}",
      "DownstreamScheme": "http",
      "DownstreamHostAndPorts": [
        {
          "Host": "host.docker.internal",
          "Port": 50002
        }
      ],
      "UpstreamPathTemplate": "/cdn-api/{catchAll}"
    },
    {
      "DownstreamPathTemplate": "/api/{catchAll}",
      "DownstreamScheme": "http",
      "DownstreamHostAndPorts": [
        {
          "Host": "host.docker.internal",
          "Port": 50003
        }
      ],
      "UpstreamPathTemplate": "/system-api/{catchAll}"
    },
    {
      "DownstreamPathTemplate": "/api/{catchAll}",
      "DownstreamScheme": "http",
      "DownstreamHostAndPorts": [
        {
          "Host": "host.docker.internal",
          "Port": 50004
        }
      ],
      "UpstreamPathTemplate": "/products-api/{catchAll}"
    },
    {
      "DownstreamPathTemplate": "/api/{catchAll}",
      "DownstreamScheme": "http",
      "DownstreamHostAndPorts": [
        {
          "Host": "host.docker.internal",
          "Port": 50005
        }
      ],
      "UpstreamPathTemplate": "/promotions-api/{catchAll}"
    },
    {
      "DownstreamPathTemplate": "/api/{catchAll}",
      "DownstreamScheme": "http",
      "DownstreamHostAndPorts": [
        {
          "Host": "host.docker.internal",
          "Port": 50006
        }
      ],
      "UpstreamPathTemplate": "/invoices-api/{catchAll}"
    },
    {
      "DownstreamPathTemplate": "/api/{catchAll}",
      "DownstreamScheme": "http",
      "DownstreamHostAndPorts": [
        {
          "Host": "host.docker.internal",
          "Port": 50007
        }
      ],
      "UpstreamPathTemplate": "/warehouse-api/{catchAll}"
    }
  ],
  "GlobalConfiguration": {
    "BaseUrl": "http://host.docker.internal"
  }
}
